ribbon/__init__.py
ribbon/config.py
ribbon/deserialize_and_run.py
ribbon/runner.py
ribbon/utils.py
ribbon/batch/__init__.py
ribbon/batch/queue_utils.py
ribbon/batch/batch_scripts/sge_submit.sh
ribbon/batch/batch_scripts/slurm_submit.sh
ribbon_toolkit-0.2.4.dist-info/licenses/LICENSE
ribbon_toolkit-0.2.4.dist-info/METADATA
ribbon_toolkit-0.2.4.dist-info/WHEEL
ribbon_toolkit-0.2.4.dist-info/top_level.txt
ribbon_toolkit-0.2.4.dist-info/RECORD
